platoon/__init__.py
platoon-0.0.0.dist-info/METADATA
platoon-0.0.0.dist-info/WHEEL
platoon-0.0.0.dist-info/RECORD
